LICENSE
MANIFEST.in
README.rst
buildout.cfg
setup.py
version.txt
bob/__init__.py
bob.db.fargo.egg-info/PKG-INFO
bob.db.fargo.egg-info/SOURCES.txt
bob.db.fargo.egg-info/dependency_links.txt
bob.db.fargo.egg-info/entry_points.txt
bob.db.fargo.egg-info/not-zip-safe
bob.db.fargo.egg-info/requires.txt
bob.db.fargo.egg-info/top_level.txt
bob/db/__init__.py
bob/db/fargo/__init__.py
bob/db/fargo/camera.py
bob/db/fargo/create.py
bob/db/fargo/driver.py
bob/db/fargo/models.py
bob/db/fargo/query.py
bob/db/fargo/test.py
bob/db/fargo/utils.py
bob/db/fargo/scripts/__init__.py
bob/db/fargo/scripts/extract_images_frontal.py
bob/db/fargo/scripts/extract_images_pose_varying.py